{
  "aggregate": {
    "timestamp": "2019-12-24T11:03:02.493Z",
    "scenariosCreated": 473,
    "scenariosCompleted": 424,
    "requestsCompleted": 1284,
    "latency": {
      "min": 52,
      "max": 74897.8,
      "median": 1618,
      "p95": 45641.6,
      "p99": 68929.7
    },
    "rps": {
      "count": 1333,
      "mean": 10.14
    },
    "scenarioDuration": {
      "min": 699,
      "max": 78088.8,
      "median": 19310.8,
      "p95": 62315.6,
      "p99": 75152.6
    },
    "scenarioCounts": {
      "0": 473
    },
    "errors": {
      "ETIMEDOUT": 26,
      "ECONNRESET": 23
    },
    "codes": {
      "200": 945,
      "400": 118,
      "403": 34,
      "500": 187
    },
    "matches": 0,
    "customStats": {},
    "counters": {},
    "scenariosAvoided": 0,
    "phases": [
      {
        "duration": 20,
        "arrivalRate": 5,
        "name": "Warm up phase"
      },
      {
        "duration": 10,
        "arrivalRate": 5,
        "rampTo": 20,
        "name": "Increased rate"
      },
      {
        "duration": 10,
        "arrivalRate": 2,
        "name": "Reduced rate"
      },
      {
        "duration": 10,
        "arrivalRate": 2,
        "rampTo": 30,
        "name": "Increased rate"
      },
      {
        "duration": 10,
        "arrivalRate": 5,
        "name": "Sustained low rate"
      }
    ]
  },
  "intermediate": [
    {
      "timestamp": "2019-12-24T11:01:00.755Z",
      "scenariosCreated": 49,
      "scenariosCompleted": 15,
      "requestsCompleted": 81,
      "latency": {
        "min": 82.7,
        "max": 5613.9,
        "median": 284.5,
        "p95": 4297.3,
        "p99": 5581.3
      },
      "rps": {
        "count": 113,
        "mean": 11.63
      },
      "scenarioDuration": {
        "min": 1160.8,
        "max": 7234.9,
        "median": 6139.3,
        "p95": 7183.7,
        "p99": 7234.9
      },
      "scenarioCounts": {
        "0": 49
      },
      "errors": {},
      "codes": {
        "200": 65,
        "400": 2,
        "500": 14
      },
      "matches": 0,
      "latencies": [
        379764400,
        216910301,
        203619400,
        195659399,
        199063701,
        200460101,
        194280300,
        199526699,
        184284000,
        197963200,
        203462001,
        257159501,
        179789801,
        183521699,
        221429700,
        236471500,
        221028399,
        226031800,
        238547000,
        209981201,
        214715400,
        194330299,
        3304935701,
        267096600,
        3116319700,
        3301211300,
        4010543700,
        426625101,
        4178890700,
        322923599,
        3890223101,
        3214721800,
        246953800,
        3159370500,
        218536100,
        3313151600,
        3111976999,
        428938100,
        82653401,
        87289601,
        3136834200,
        365059701,
        281764400,
        203754699,
        191671099,
        228124001,
        223958301,
        200082200,
        202068000,
        3816215100,
        231490701,
        2724259199,
        198963599,
        2357967599,
        2246477800,
        2002582501,
        1293144501,
        1919803301,
        2375345399,
        2126138199,
        2039175300,
        1113218100,
        308103901,
        1165354001,
        4441927399,
        358568200,
        267210101,
        297443901,
        284471599,
        1416141199,
        5076424801,
        279690999,
        264945499,
        328560400,
        286743599,
        1425374100,
        5508751900,
        236544499,
        200155700,
        5613924700,
        336487201
      ],
      "customStats": {},
      "counters": {},
      "concurrency": 34,
      "pendingRequests": 32,
      "scenariosAvoided": 0
    },
    {
      "timestamp": "2019-12-24T11:01:10.790Z",
      "scenariosCreated": 50,
      "scenariosCompleted": 39,
      "requestsCompleted": 137,
      "latency": {
        "min": 104.7,
        "max": 11454.5,
        "median": 776.1,
        "p95": 8102.5,
        "p99": 10074.8
      },
      "rps": {
        "count": 145,
        "mean": 14.51
      },
      "scenarioDuration": {
        "min": 1087.5,
        "max": 12536.3,
        "median": 8808.9,
        "p95": 10758.9,
        "p99": 12536.3
      },
      "scenarioCounts": {
        "0": 50
      },
      "errors": {},
      "codes": {
        "200": 89,
        "400": 10,
        "500": 38
      },
      "matches": 0,
      "latencies": [
        290719500,
        238079300,
        6142285600,
        328945100,
        251688100,
        5197691901,
        6159580399,
        386685799,
        230890299,
        6345195901,
        491773501,
        349125700,
        7294621800,
        339942499,
        5255080399,
        6453545800,
        3174431201,
        5172037100,
        412439200,
        337958299,
        5373164801,
        5801183499,
        301346601,
        3022733101,
        1730554400,
        2065617601,
        2773897001,
        1683276000,
        1502559300,
        459340100,
        340722800,
        7763355301,
        345358401,
        5458797100,
        1250954399,
        281186800,
        1387619401,
        1304284099,
        1417412700,
        339883400,
        178759399,
        6524761199,
        396140700,
        279502299,
        1447729601,
        1391172501,
        341831000,
        247025201,
        6682012400,
        6904760899,
        8104451700,
        6247983300,
        389884900,
        1363318299,
        6621272301,
        403986299,
        6299617199,
        1503023400,
        326853299,
        385486701,
        274704800,
        246093000,
        104735499,
        333025199,
        136932800,
        575127701,
        485069000,
        425771000,
        295437200,
        7568143701,
        332027400,
        548415300,
        406768899,
        7214107101,
        198190500,
        209699999,
        510993800,
        3206992001,
        409725299,
        123597200,
        354776399,
        306697600,
        289196500,
        307968199,
        3196093501,
        3141707599,
        328165901,
        3141966300,
        3185664899,
        364632300,
        134931701,
        274557000,
        3066453201,
        2936014801,
        1399503601,
        7825314100,
        6232840200,
        194902499,
        370174799,
        8213792099,
        7431788899,
        394637801,
        297520900,
        139413400,
        340584800,
        7222788599,
        9143221301,
        1500365799,
        9041091801,
        435604601,
        302532401,
        6839506000,
        459271499,
        133632400,
        8098970101,
        341764801,
        337404801,
        392981801,
        9868682699,
        7496417901,
        1456222401,
        1413814700,
        8005825200,
        1527897600,
        1478387400,
        9427762700,
        7496384799,
        1563949799,
        776124899,
        998483000,
        288874701,
        492655300,
        698797900,
        7156073399,
        7878724700,
        254694801,
        11454546900
      ],
      "customStats": {},
      "counters": {},
      "concurrency": 45,
      "pendingRequests": 40,
      "scenariosAvoided": 0
    },
    {
      "timestamp": "2019-12-24T11:01:20.790Z",
      "scenariosCreated": 116,
      "scenariosCompleted": 100,
      "requestsCompleted": 304,
      "latency": {
        "min": 57.9,
        "max": 10610.5,
        "median": 461.4,
        "p95": 6944.6,
        "p99": 9070.4
      },
      "rps": {
        "count": 305,
        "mean": 30.72
      },
      "scenarioDuration": {
        "min": 699,
        "max": 14957.4,
        "median": 2114.9,
        "p95": 13276.3,
        "p99": 14823.2
      },
      "scenarioCounts": {
        "0": 116
      },
      "errors": {},
      "codes": {
        "200": 206,
        "400": 51,
        "403": 10,
        "500": 37
      },
      "matches": 0,
      "latencies": [
        6945758200,
        7899411501,
        10354680199,
        7861090201,
        502394800,
        293717199,
        349265700,
        649284500,
        427282200,
        453836000,
        8017619301,
        569268700,
        728456899,
        738076600,
        780891100,
        774207600,
        3410810701,
        3263601000,
        205792500,
        7484206599,
        3262049899,
        177649700,
        362874500,
        416717000,
        521718301,
        598163400,
        3264223500,
        351768299,
        688355600,
        160618001,
        288533799,
        5835903300,
        130803101,
        8616970100,
        6944087300,
        242238001,
        8009436300,
        508439500,
        286320200,
        448437601,
        7405369201,
        496046300,
        3419842801,
        3105409500,
        3478388800,
        2617920001,
        2644946100,
        7684804201,
        2243119801,
        2284609700,
        2906725201,
        96017401,
        2544524100,
        2368478599,
        2999575101,
        2161518201,
        1647626500,
        178969301,
        240522499,
        252858800,
        654562100,
        273074200,
        596441600,
        637403000,
        8986959100,
        409930100,
        342607500,
        409269500,
        417105100,
        314194301,
        380018300,
        233970801,
        291696600,
        327510000,
        351155600,
        6608483001,
        1401626600,
        5346075300,
        194642301,
        407821999,
        9168277700,
        349596801,
        388761399,
        141607400,
        6166308799,
        338761900,
        175011200,
        8907314000,
        154334301,
        201145300,
        174549100,
        1642854601,
        458044100,
        6390750101,
        371534699,
        6875823600,
        1528676300,
        1687611301,
        5679032701,
        1395102300,
        1484762299,
        1580415200,
        459726499,
        101908900,
        110992799,
        421365201,
        90718301,
        392915000,
        390859001,
        393194001,
        81931399,
        231632400,
        202857700,
        210523200,
        200111700,
        232824699,
        10610491000,
        220835799,
        104928901,
        211441301,
        277604501,
        1641094900,
        234452501,
        1409941700,
        255432601,
        1401567400,
        1381157400,
        367945499,
        144527500,
        139721300,
        348888900,
        122183300,
        79985400,
        284966600,
        265209601,
        109284599,
        246012500,
        196484901,
        190969899,
        281455601,
        385866700,
        266110601,
        300239201,
        5734415000,
        4012938601,
        5334340999,
        333772999,
        128698500,
        272263699,
        106084599,
        281537799,
        6253867199,
        241764101,
        5730300200,
        115232900,
        341176300,
        5768976701,
        82137399,
        6347941801,
        5738623400,
        85652400,
        386538199,
        4327485901,
        463102099,
        434634801,
        383471001,
        449011100,
        95870601,
        7642428800,
        57910201,
        69772901,
        474278001,
        489821801,
        629480700,
        761973100,
        600860801,
        3331490000,
        184741000,
        573927900,
        577151599,
        3153322200,
        3133579701,
        100853100,
        3061196201,
        95248100,
        663476099,
        3460265300,
        154767599,
        697889899,
        702268600,
        66145499,
        784892200,
        783260899,
        683535700,
        814438699,
        812651099,
        119446900,
        780983799,
        692778400,
        3270572300,
        2011196900,
        2028644001,
        2045414600,
        1427509501,
        1627458801,
        1591880700,
        1592276900,
        1622759401,
        840077400,
        861946201,
        284383199,
        293658001,
        301078701,
        643223700,
        659408300,
        192645901,
        829548100,
        266393801,
        334242400,
        557007100,
        1000919801,
        361851900,
        538158800,
        843021100,
        994795401,
        817734200,
        218161900,
        367098000,
        218094400,
        152137001,
        312521401,
        934265399,
        1675485800,
        828807300,
        408251699,
        463755401,
        979222201,
        980085299,
        335483700,
        176789700,
        182535500,
        129569801,
        84953100,
        368278900,
        5675825100,
        412062900,
        339956201,
        338817700,
        341897900,
        400376700,
        91364300,
        314959899,
        316053100,
        321058101,
        331523500,
        5455977300,
        164168300,
        111864900,
        388127801,
        416322999,
        1316063900,
        318090701,
        326099401,
        404504800,
        465335400,
        391287900,
        331433700,
        92883999,
        363224899,
        425072999,
        191723900,
        514596500,
        5662094899,
        499037601,
        419208801,
        579199999,
        510572501,
        323558800,
        646897899,
        714004501,
        788445799,
        617376600,
        642517299,
        757222300,
        4246041201,
        593575000,
        4328671400,
        682745500,
        712860200,
        513539099,
        423482000,
        491062399,
        3857117900,
        436024101,
        478652601,
        418527799,
        3966902201,
        404878799,
        473429201,
        434322801,
        968160801,
        3556111000,
        458519800,
        407820201
      ],
      "customStats": {},
      "counters": {},
      "concurrency": 61,
      "pendingRequests": 41,
      "scenariosAvoided": 0
    },
    {
      "timestamp": "2019-12-24T11:01:30.785Z",
      "scenariosCreated": 28,
      "scenariosCompleted": 16,
      "requestsCompleted": 65,
      "latency": {
        "min": 109,
        "max": 11272.5,
        "median": 538.2,
        "p95": 10724.5,
        "p99": 11267.8
      },
      "rps": {
        "count": 97,
        "mean": 9.77
      },
      "scenarioDuration": {
        "min": 1182.4,
        "max": 10205.6,
        "median": 7144.5,
        "p95": 10176.8,
        "p99": 10205.6
      },
      "scenarioCounts": {
        "0": 28
      },
      "errors": {},
      "codes": {
        "200": 48,
        "403": 8,
        "500": 9
      },
      "matches": 0,
      "latencies": [
        538187400,
        4866182799,
        198000099,
        534526201,
        192712599,
        134425800,
        579650799,
        227054601,
        230310200,
        703173600,
        676585299,
        172761900,
        661202100,
        109039801,
        604847400,
        609652299,
        145957899,
        654812900,
        499764500,
        451160100,
        462910599,
        442353399,
        492226399,
        419901100,
        475904501,
        456607000,
        2793697899,
        2889435001,
        318804800,
        3225821600,
        3254217900,
        1374786500,
        1361559300,
        341267800,
        3682232001,
        3394858100,
        2889467601,
        2647030801,
        2794068900,
        2909414400,
        2455238700,
        1267010800,
        1243477899,
        2353483400,
        419240899,
        237240799,
        1465081200,
        681547901,
        504775399,
        500699800,
        357465101,
        388350200,
        447126100,
        383078799,
        494520600,
        350578100,
        9429627800,
        731839300,
        429836101,
        523263800,
        10594419200,
        11114861400,
        509796801,
        11240717600,
        11272525401
      ],
      "customStats": {},
      "counters": {},
      "concurrency": 73,
      "pendingRequests": 73,
      "scenariosAvoided": 0
    },
    {
      "timestamp": "2019-12-24T11:01:40.790Z",
      "scenariosCreated": 147,
      "scenariosCompleted": 57,
      "requestsCompleted": 166,
      "latency": {
        "min": 131.8,
        "max": 16677.2,
        "median": 2908.5,
        "p95": 15390.6,
        "p99": 16558.6
      },
      "rps": {
        "count": 256,
        "mean": 25.63
      },
      "scenarioDuration": {
        "min": 1748.8,
        "max": 20953.4,
        "median": 18676.7,
        "p95": 20520.7,
        "p99": 20941
      },
      "scenarioCounts": {
        "0": 147
      },
      "errors": {},
      "codes": {
        "200": 110,
        "400": 3,
        "500": 53
      },
      "matches": 0,
      "latencies": [
        524237799,
        11540003699,
        12013975400,
        466122800,
        3092581001,
        475416899,
        299910400,
        526062399,
        552644400,
        367486701,
        470029901,
        3436058201,
        3017922800,
        2740156300,
        2529098999,
        3271447601,
        2417794001,
        552102799,
        13861140900,
        633559300,
        620121801,
        595160100,
        14175016800,
        12264385400,
        645463301,
        566763999,
        395435901,
        12559962000,
        534560200,
        531172099,
        558803301,
        15032830799,
        512226399,
        681061600,
        13109600600,
        815558999,
        704391399,
        15082716100,
        13392795400,
        15008290599,
        380794600,
        475676200,
        13648174901,
        13297243700,
        14438326301,
        14008728699,
        14247766000,
        14224636000,
        538533699,
        660627900,
        13488711300,
        15230496100,
        639747700,
        683485600,
        14682438701,
        13817459899,
        14381958400,
        495762801,
        496767101,
        15712071001,
        703559501,
        14616637300,
        479473700,
        518906600,
        437020500,
        493242899,
        14945110200,
        535855200,
        15192011900,
        15146794000,
        596159700,
        571865301,
        14328509700,
        637476300,
        15734380100,
        14018491600,
        686832500,
        14407067500,
        614369501,
        13811512400,
        14656529600,
        14403167300,
        14660846500,
        14413841499,
        16288818100,
        13664771001,
        15509858201,
        15491501200,
        14092669301,
        867184201,
        986505199,
        965430900,
        952312201,
        780521001,
        14876676000,
        15365329300,
        15026580700,
        16677186000,
        14172487000,
        14507120800,
        14802342600,
        14840403199,
        15582700100,
        16609968799,
        13477310501,
        15225138999,
        952118899,
        986569400,
        959999700,
        1010761800,
        842519200,
        879937399,
        865497099,
        879549099,
        832664499,
        3429484200,
        3320454000,
        4028014700,
        131796100,
        4126477701,
        3762463501,
        3686932600,
        3182025899,
        2936399300,
        3387604801,
        3292567800,
        3905031399,
        3554999400,
        3275856399,
        3246560100,
        2962485400,
        3499602300,
        3807430600,
        3858712000,
        3646622100,
        2915623700,
        3211287699,
        3610910000,
        4106049800,
        3659668600,
        2732104101,
        2732798200,
        2678666600,
        2831482800,
        2901289701,
        2744844999,
        2801506301,
        3721502500,
        2662029100,
        3066568300,
        2517176600,
        2669710599,
        2677819299,
        2553109600,
        2716576800,
        2462432500,
        2660915200,
        2822614000,
        2569880900,
        2695171799,
        2737789199,
        2649406800,
        2631538300,
        2831729400,
        2742807899,
        2780480000
      ],
      "customStats": {},
      "counters": {},
      "concurrency": 163,
      "pendingRequests": 163,
      "scenariosAvoided": 0
    },
    {
      "timestamp": "2019-12-24T11:01:50.785Z",
      "scenariosCreated": 76,
      "scenariosCompleted": 9,
      "requestsCompleted": 142,
      "latency": {
        "min": 52.7,
        "max": 10226.4,
        "median": 6340.6,
        "p95": 7987.4,
        "p99": 9224.1
      },
      "rps": {
        "count": 209,
        "mean": 21.05
      },
      "scenarioDuration": {
        "min": 4782.5,
        "max": 23579.3,
        "median": 8000.5,
        "p95": 23579.3,
        "p99": 23579.3
      },
      "scenarioCounts": {
        "0": 76
      },
      "errors": {},
      "codes": {
        "200": 94,
        "400": 38,
        "403": 10
      },
      "matches": 0,
      "latencies": [
        3891058800,
        4155313400,
        4494161199,
        5319858301,
        5546060999,
        5548041500,
        5631931701,
        5649618500,
        6034233999,
        6318099800,
        6578852301,
        6916652800,
        6523812000,
        6834378200,
        7081294900,
        6893455500,
        6594609601,
        7000249601,
        7089774201,
        6659798001,
        6841926800,
        7228487000,
        6355648200,
        6598306301,
        6245323300,
        6287787600,
        6224894100,
        6679584000,
        6672225401,
        6325578801,
        6844662399,
        6756249999,
        6586627799,
        6791195200,
        6807103999,
        6489958501,
        6233664401,
        6649227400,
        6159538501,
        6186643900,
        6677057699,
        6787701900,
        6704734801,
        6765155299,
        6506315600,
        6888717800,
        6743273300,
        6555879599,
        6807357701,
        6675802500,
        202783199,
        6693751399,
        6742876201,
        6763899300,
        268057600,
        7346307999,
        231139001,
        6837059300,
        236479599,
        240732900,
        7145769299,
        212853900,
        7254387800,
        7228293700,
        7229070501,
        202447900,
        182802899,
        190018300,
        7623758500,
        183454401,
        195361501,
        176744600,
        7617544100,
        186621401,
        131594200,
        141684000,
        145882200,
        7851491599,
        130326100,
        7842308600,
        7825703400,
        7849062800,
        109192299,
        114653100,
        7880434900,
        130234899,
        149529199,
        183384401,
        196580699,
        8046408500,
        7997951799,
        7980379500,
        8002783801,
        99900499,
        105293299,
        130433901,
        8007712099,
        8016633199,
        110558299,
        6640456100,
        6441698300,
        7101753600,
        7396692400,
        7104894699,
        7079105300,
        180042600,
        4153042599,
        139069001,
        191345200,
        169682700,
        7192535300,
        6888608500,
        7194326000,
        174655500,
        231524100,
        263685900,
        191836300,
        134561700,
        140707400,
        4466831500,
        165723200,
        7493722601,
        7550844101,
        167796600,
        5511967701,
        103773200,
        7476863401,
        7505205099,
        74264600,
        100659300,
        9136981601,
        5912006100,
        64344300,
        5561072999,
        77055100,
        4603876600,
        7610560100,
        92307300,
        73654500,
        73212399,
        52727901,
        10226391900
      ],
      "customStats": {},
      "counters": {},
      "concurrency": 230,
      "pendingRequests": 230,
      "scenariosAvoided": 0
    },
    {
      "timestamp": "2019-12-24T11:02:00.817Z",
      "scenariosCreated": 7,
      "scenariosCompleted": 2,
      "requestsCompleted": 12,
      "latency": {
        "min": 65.8,
        "max": 33675.6,
        "median": 12336.7,
        "p95": 31842.9,
        "p99": 33675.6
      },
      "rps": {
        "count": 17,
        "mean": 1.7
      },
      "scenarioDuration": {
        "min": 22798.6,
        "max": 22880.7,
        "median": 22839.6,
        "p95": 22880.7,
        "p99": 22880.7
      },
      "scenarioCounts": {
        "0": 7
      },
      "errors": {},
      "codes": {
        "200": 11,
        "400": 1
      },
      "matches": 0,
      "latencies": [
        10640323199,
        10454445100,
        12202923399,
        12470493300,
        13309960599,
        65788800,
        9387432599,
        9855625400,
        33675600000,
        14293670200,
        15348133900,
        14382441800
      ],
      "customStats": {},
      "counters": {},
      "concurrency": 235,
      "pendingRequests": 235,
      "scenariosAvoided": 0
    },
    {
      "timestamp": "2019-12-24T11:02:10.758Z",
      "scenariosCreated": 0,
      "scenariosCompleted": 3,
      "requestsCompleted": 7,
      "latency": {
        "min": 1175,
        "max": 37418.6,
        "median": 24511.7,
        "p95": 37418.6,
        "p99": 37418.6
      },
      "rps": {
        "count": 3,
        "mean": 0.37
      },
      "scenarioDuration": {
        "min": 28200.2,
        "max": 39640.8,
        "median": 38090.3,
        "p95": 39640.8,
        "p99": 39640.8
      },
      "scenarioCounts": {},
      "errors": {
        "ETIMEDOUT": 19,
        "ECONNRESET": 4
      },
      "codes": {
        "200": 7
      },
      "matches": 0,
      "latencies": [
        2473998100,
        37418632901,
        1174988301,
        19444411900,
        25502051201,
        27570243300,
        24511749700
      ],
      "customStats": {},
      "counters": {},
      "concurrency": 209,
      "pendingRequests": 231,
      "scenariosAvoided": 0
    },
    {
      "timestamp": "2019-12-24T11:02:20.762Z",
      "scenariosCreated": 0,
      "scenariosCompleted": 5,
      "requestsCompleted": 18,
      "latency": {
        "min": 1252.1,
        "max": 47503.8,
        "median": 43745.8,
        "p95": 46846.8,
        "p99": 47503.8
      },
      "rps": {
        "count": 14,
        "mean": 1.46
      },
      "scenarioDuration": {
        "min": 41261.1,
        "max": 49239.1,
        "median": 46265.2,
        "p95": 49239.1,
        "p99": 49239.1
      },
      "scenarioCounts": {},
      "errors": {
        "ECONNRESET": 2,
        "ETIMEDOUT": 7
      },
      "codes": {
        "200": 18
      },
      "matches": 0,
      "latencies": [
        42588769400,
        26073981099,
        45288199301,
        1773057001,
        45861199699,
        1798072000,
        2366155600,
        43671366700,
        32531666201,
        44108311599,
        44214665501,
        44256962100,
        44215557499,
        44103785299,
        47503792000,
        43820142701,
        1252141199,
        33378918799
      ],
      "customStats": {},
      "counters": {},
      "concurrency": 195,
      "pendingRequests": 227,
      "scenariosAvoided": 0
    },
    {
      "timestamp": "2019-12-24T11:02:30.834Z",
      "scenariosCreated": 0,
      "scenariosCompleted": 83,
      "requestsCompleted": 182,
      "latency": {
        "min": 52,
        "max": 50867.9,
        "median": 41917.9,
        "p95": 49144.8,
        "p99": 50054
      },
      "rps": {
        "count": 93,
        "mean": 9.84
      },
      "scenarioDuration": {
        "min": 44571.3,
        "max": 53538.5,
        "median": 49408.7,
        "p95": 52206,
        "p99": 53179.5
      },
      "scenarioCounts": {},
      "errors": {},
      "codes": {
        "200": 157,
        "400": 12,
        "403": 4,
        "500": 9
      },
      "matches": 0,
      "latencies": [
        1920669400,
        1867788599,
        1928006700,
        1941172800,
        1914104500,
        1983493900,
        45296109899,
        2074329500,
        36054174800,
        44775171701,
        46271587800,
        45080795599,
        44829084600,
        45342970500,
        44844560899,
        46420427299,
        45489158999,
        46510333300,
        45211295899,
        45688601299,
        46216402099,
        43929452999,
        43929330000,
        43867661800,
        46911362200,
        43956473601,
        45928936800,
        46389259899,
        46186907201,
        46769269800,
        44281579601,
        44020092601,
        45212567500,
        46367492000,
        45845411000,
        45934472001,
        45621455100,
        45134614999,
        43978925501,
        43958302401,
        45488284000,
        1405064399,
        49577060700,
        49638029100,
        1273395801,
        1285194800,
        1276105700,
        1277794800,
        42375156299,
        42667034999,
        1162751401,
        1163578300,
        1153619200,
        42107098200,
        1153647000,
        1192440599,
        1118029401,
        1186330500,
        1084919900,
        1157644199,
        1152069001,
        1147944999,
        1183519901,
        1204759300,
        1178205999,
        40903378501,
        1110261900,
        1150503900,
        1092432800,
        1183161600,
        1115115001,
        1118474601,
        1099130401,
        1085829801,
        1110218599,
        1080340000,
        1091237200,
        1124533700,
        1085300001,
        1097202401,
        1109836099,
        42287690700,
        41998933199,
        38415730199,
        41826326600,
        41677378599,
        1383648201,
        1365816001,
        1358805600,
        1478866101,
        39091717100,
        39193974599,
        46312735300,
        46437951100,
        39397217399,
        40513163600,
        40708004701,
        55560000,
        39785427400,
        46890804900,
        1367755701,
        1416851201,
        1388443100,
        1436905500,
        43401018201,
        47627691499,
        52030401,
        41669951400,
        48713829400,
        41753000500,
        48804856700,
        42681902801,
        48908394100,
        41960711101,
        48996870601,
        48991977600,
        1448726099,
        43240397100,
        42358709500,
        49101901999,
        42107261700,
        42165999100,
        42080886600,
        111737400,
        49209139400,
        185280600,
        42188311301,
        49251761800,
        49232467099,
        42671230700,
        45926263901,
        42297452400,
        42257237200,
        42445205500,
        42311335800,
        43375711000,
        253614801,
        49304205600,
        42182903299,
        42205219501,
        159389900,
        42332923500,
        42829505900,
        42417696199,
        42455478201,
        217554400,
        42394376101,
        166062801,
        42505539601,
        50192448799,
        42543191100,
        278905899,
        275163999,
        41539687100,
        293845599,
        49759796999,
        42145230900,
        41778470399,
        41622293900,
        41807080800,
        42590289200,
        41912696400,
        42949133399,
        42610447701,
        42525016799,
        183901100,
        41923172100,
        41792149701,
        149128901,
        42329786801,
        38480089001,
        39084778199,
        202990600,
        42640592899,
        306630800,
        40579506100,
        39555189900,
        42313992701,
        1715997401,
        260571101,
        50867905101,
        2648270599
      ],
      "customStats": {},
      "counters": {},
      "concurrency": 112,
      "pendingRequests": 138,
      "scenariosAvoided": 0
    },
    {
      "timestamp": "2019-12-24T11:02:40.883Z",
      "scenariosCreated": 0,
      "scenariosCompleted": 53,
      "requestsCompleted": 95,
      "latency": {
        "min": 117.3,
        "max": 74897.8,
        "median": 4407.7,
        "p95": 67660.6,
        "p99": 74241.9
      },
      "rps": {
        "count": 45,
        "mean": 4.54
      },
      "scenarioDuration": {
        "min": 50863.7,
        "max": 75119.8,
        "median": 54757.7,
        "p95": 59608,
        "p99": 74665.4
      },
      "scenarioCounts": {},
      "errors": {},
      "codes": {
        "200": 66,
        "400": 1,
        "403": 2,
        "500": 26
      },
      "matches": 0,
      "latencies": [
        278411600,
        49375611800,
        1522219300,
        42418746300,
        43200631200,
        42383760500,
        126717101,
        117309399,
        42282518701,
        42612855200,
        42855675300,
        42781036901,
        42721052600,
        42828260800,
        45287584701,
        42799761500,
        2104797401,
        1737716399,
        4873066200,
        1827816801,
        44476440799,
        2427897101,
        44914052700,
        44674401500,
        44934247599,
        1831588601,
        1802773499,
        44727489901,
        46089688800,
        45001178401,
        45108572800,
        1617599000,
        1531225100,
        1626497201,
        2152812200,
        1483838401,
        1049773800,
        2847360100,
        2853127000,
        2956269499,
        2916454401,
        2821659199,
        2849296701,
        2789879700,
        2640527600,
        2491853000,
        2275542800,
        2230279001,
        2347153200,
        2291995101,
        2318886401,
        3938462801,
        3931463799,
        4156507301,
        4098676800,
        4236023501,
        53892547900,
        4477258800,
        46962598000,
        4404755500,
        4347555600,
        4407729500,
        4492192399,
        4507272700,
        4542422900,
        4701663801,
        72870347100,
        4816927799,
        47531213500,
        48216700000,
        48217181599,
        44292055300,
        48351021899,
        47503542199,
        48780348100,
        1779299701,
        48827311899,
        1722306599,
        1736471801,
        1639491800,
        1505826100,
        72250001199,
        72790190700,
        73440218800,
        1496824501,
        1589492999,
        1593706400,
        1541518100,
        1618440900,
        44965403001,
        44980695299,
        45541595501,
        46044958799,
        39818594600,
        74897795800
      ],
      "customStats": {},
      "counters": {},
      "concurrency": 59,
      "pendingRequests": 88,
      "scenariosAvoided": 0
    },
    {
      "timestamp": "2019-12-24T11:02:50.884Z",
      "scenariosCreated": 0,
      "scenariosCompleted": 42,
      "requestsCompleted": 75,
      "latency": {
        "min": 1058.9,
        "max": 72552.4,
        "median": 1542.1,
        "p95": 71073.7,
        "p99": 72451.4
      },
      "rps": {
        "count": 36,
        "mean": 3.61
      },
      "scenarioDuration": {
        "min": 52899.7,
        "max": 78088.8,
        "median": 61840,
        "p95": 75601,
        "p99": 78088.8
      },
      "scenarioCounts": {},
      "errors": {
        "ECONNRESET": 1
      },
      "codes": {
        "200": 74,
        "500": 1
      },
      "matches": 0,
      "latencies": [
        48544955599,
        1375020800,
        1421086100,
        1602127400,
        69417836501,
        68986791299,
        70493124000,
        34330057000,
        72148347099,
        71720520599,
        1430874100,
        1563509499,
        69519256200,
        71267164201,
        72552354899,
        68818868099,
        1598252700,
        31099754600,
        62271299300,
        15233658300,
        62464152100,
        14005357300,
        1542077901,
        1749476700,
        12298069400,
        33423092701,
        1494408400,
        17994386401,
        16191979500,
        29940511199,
        16135830600,
        1412363800,
        15894996499,
        12051422301,
        24429714899,
        13001359801,
        12082047001,
        12041836000,
        12090254400,
        13885051401,
        12114100600,
        11955532400,
        6962568100,
        1240766601,
        1269378200,
        1273332799,
        1323349400,
        1239588700,
        1220935401,
        1247860799,
        1172439799,
        1312961099,
        1334330100,
        1282622701,
        1270743100,
        1196609499,
        1251601600,
        1130541499,
        1138093601,
        1112191300,
        1070865501,
        1113874501,
        1163744099,
        1174793799,
        1131888000,
        1110292000,
        1161313701,
        1108827100,
        1112286501,
        1058851900,
        1140690600,
        1128504299,
        1116704999,
        1246911299,
        1304099300
      ],
      "customStats": {},
      "counters": {},
      "concurrency": 16,
      "pendingRequests": 49,
      "scenariosAvoided": 0
    },
    {
      "timestamp": "2019-12-24T11:03:00.896Z",
      "scenariosCreated": 0,
      "scenariosCompleted": 0,
      "requestsCompleted": 0,
      "latency": {
        "min": null,
        "max": null,
        "median": null,
        "p95": null,
        "p99": null
      },
      "rps": {
        "count": 0,
        "mean": null
      },
      "scenarioDuration": {
        "min": null,
        "max": null,
        "median": null,
        "p95": null,
        "p99": null
      },
      "scenarioCounts": {},
      "errors": {
        "ECONNRESET": 8
      },
      "codes": {},
      "matches": 0,
      "latencies": [],
      "customStats": {},
      "counters": {},
      "concurrency": 8,
      "pendingRequests": 49,
      "scenariosAvoided": 0
    },
    {
      "timestamp": "2019-12-24T11:03:02.428Z",
      "scenariosCreated": 0,
      "scenariosCompleted": 0,
      "requestsCompleted": 0,
      "latency": {
        "min": null,
        "max": null,
        "median": null,
        "p95": null,
        "p99": null
      },
      "rps": {
        "count": 0,
        "mean": null
      },
      "scenarioDuration": {
        "min": null,
        "max": null,
        "median": null,
        "p95": null,
        "p99": null
      },
      "scenarioCounts": {},
      "errors": {
        "ECONNRESET": 8
      },
      "codes": {},
      "matches": 0,
      "latencies": [],
      "customStats": {},
      "counters": {},
      "concurrency": 0,
      "pendingRequests": 49,
      "scenariosAvoided": 0
    }
  ]
}